countries/__init__.py
countries/admin.py
countries/apps.py
countries/factories.py
countries/fields.py
countries/managers.py
countries/models.py
countries/shortcuts.py
countries/fixtures/all/continent.json
countries/fixtures/all/currency.json
countries/fixtures/all/language.json
countries/fixtures/all/locale.json
countries/fixtures/all/timezone.json
countries/fixtures/countries/ad.divisions.json
countries/fixtures/countries/ad.geo.json
countries/fixtures/countries/ad.names.json
countries/fixtures/countries/ae.divisions.json
countries/fixtures/countries/ae.geo.json
countries/fixtures/countries/ae.names.json
countries/fixtures/countries/af.divisions.json
countries/fixtures/countries/af.geo.json
countries/fixtures/countries/af.names.json
countries/fixtures/countries/ag.divisions.json
countries/fixtures/countries/ag.geo.json
countries/fixtures/countries/ag.names.json
countries/fixtures/countries/ai.geo.json
countries/fixtures/countries/ai.names.json
countries/fixtures/countries/al.divisions.json
countries/fixtures/countries/al.geo.json
countries/fixtures/countries/al.names.json
countries/fixtures/countries/am.divisions.json
countries/fixtures/countries/am.geo.json
countries/fixtures/countries/am.names.json
countries/fixtures/countries/ao.divisions.json
countries/fixtures/countries/ao.geo.json
countries/fixtures/countries/ao.names.json
countries/fixtures/countries/aq.divisions.json
countries/fixtures/countries/aq.geo.json
countries/fixtures/countries/aq.names.json
countries/fixtures/countries/ar.divisions.json
countries/fixtures/countries/ar.geo.json
countries/fixtures/countries/ar.names.json
countries/fixtures/countries/as.geo.json
countries/fixtures/countries/as.names.json
countries/fixtures/countries/at.divisions.json
countries/fixtures/countries/at.geo.json
countries/fixtures/countries/at.names.json
countries/fixtures/countries/au.divisions.json
countries/fixtures/countries/au.geo.json
django_countries_flavor-0.1.1.dist-info/DESCRIPTION.rst
django_countries_flavor-0.1.1.dist-info/METADATA
django_countries_flavor-0.1.1.dist-info/RECORD
django_countries_flavor-0.1.1.dist-info/WHEEL
django_countries_flavor-0.1.1.dist-info/metadata.json
django_countries_flavor-0.1.1.dist-info/top_level.txt
