Metadata-Version: 2.0
Name: django-countries-flavor
Version: 0.1.1
Summary: A Django application that provides a data collection for internationalization and localization purposes.
Home-page: https://github.com/flavors/django-countries/
Author: mongkok
Author-email: domake.io@gmail.com
License: MIT
Platform: UNKNOWN
Classifier: Development Status :: 1 - Planning
Classifier: Environment :: Web Environment
Classifier: Intended Audience :: Developers
Classifier: License :: OSI Approved :: MIT License
Classifier: Operating System :: OS Independent
Classifier: Programming Language :: Python
Classifier: Programming Language :: Python :: 3
Classifier: Programming Language :: Python :: 3.4
Classifier: Programming Language :: Python :: 3.5
Classifier: Programming Language :: Python :: 3.6
Classifier: Programming Language :: Python :: 3.7
Classifier: Framework :: Django
Requires-Dist: Django (>=1.9)
Requires-Dist: psycopg2 (>=2.6.2)
Requires-Dist: requests (>=1.1.0)
